setup.cfg
setup.py
bgscripts/__init__.py
bgscripts/randomizer.py
bgscripts.egg-info/PKG-INFO
bgscripts.egg-info/SOURCES.txt
bgscripts.egg-info/dependency_links.txt
bgscripts.egg-info/entry_points.txt
bgscripts.egg-info/requires.txt
bgscripts.egg-info/top_level.txt
bgscripts/utils/__init__.py
bgscripts/utils/loaddata.py
bgscripts/utils/referencegenome.py