Metadata-Version: 1.1
Name: bgscripts
Version: 0.2.0
Summary: Generic python scripts used at Biomedical Genomics group
Home-page: https://bitbucket.org/bgframework/bgscripts
Author: Jordi Deu-Pons
Author-email: jordi.deu@upf.edu
License: Apache License 2
Download-URL: https://bitbucket.org/bgframework/bgscripts/get/0.2.0.tar.gz
Platform: UNKNOWN
